mopidyartfetch/__init__.py
mopidyartfetch/blank.png
mopidyartfetch/mopidyartfetch.py
mopidyartfetch-0.1.dist-info/METADATA
mopidyartfetch-0.1.dist-info/WHEEL
mopidyartfetch-0.1.dist-info/top_level.txt
mopidyartfetch-0.1.dist-info/RECORD
